serverz_mcp/__init__.py
serverz_mcp/log.py
serverz_mcp/server/__init__.py
serverz_mcp/server/__main__.py
serverz_mcp/server/scheduler_task.py
serverz_mcp/server/mcp_server/__init__.py
serverz_mcp/server/mcp_server/mcp_demo.py
serverz_mcp-0.1.2.dist-info/METADATA
serverz_mcp-0.1.2.dist-info/WHEEL
serverz_mcp-0.1.2.dist-info/top_level.txt
serverz_mcp-0.1.2.dist-info/RECORD
