Metadata-Version: 2.4
Name: serverz-mcp
Version: 0.1.2
Summary: Add your description here
Requires-Python: >=3.12
Requires-Dist: anyio>=4.11.0
Requires-Dist: apscheduler>=3.11.1
Requires-Dist: dotenv>=0.9.9
Requires-Dist: fastapi>=0.121.1
Requires-Dist: mcp[cli]>=1.21.0
Requires-Dist: pro-craft>=0.2.65
Requires-Dist: pytest>=9.0.0
Requires-Dist: pytest-asyncio>=1.3.0
Requires-Dist: pytest-tornasync>=0.6.0.post2
Requires-Dist: toml>=0.10.2
Requires-Dist: uvicorn>=0.38.0
